odoo/addons/product_manufacturer/README.rst
odoo/addons/product_manufacturer/__init__.py
odoo/addons/product_manufacturer/__manifest__.py
odoo/addons/product_manufacturer/i18n/ar.po
odoo/addons/product_manufacturer/i18n/bg.po
odoo/addons/product_manufacturer/i18n/bs.po
odoo/addons/product_manufacturer/i18n/ca.po
odoo/addons/product_manufacturer/i18n/cs.po
odoo/addons/product_manufacturer/i18n/da.po
odoo/addons/product_manufacturer/i18n/de.po
odoo/addons/product_manufacturer/i18n/el.po
odoo/addons/product_manufacturer/i18n/es.po
odoo/addons/product_manufacturer/i18n/es_AR.po
odoo/addons/product_manufacturer/i18n/es_CR.po
odoo/addons/product_manufacturer/i18n/es_EC.po
odoo/addons/product_manufacturer/i18n/es_MX.po
odoo/addons/product_manufacturer/i18n/es_VE.po
odoo/addons/product_manufacturer/i18n/et.po
odoo/addons/product_manufacturer/i18n/fi.po
odoo/addons/product_manufacturer/i18n/fr.po
odoo/addons/product_manufacturer/i18n/gl.po
odoo/addons/product_manufacturer/i18n/hr.po
odoo/addons/product_manufacturer/i18n/hu.po
odoo/addons/product_manufacturer/i18n/it.po
odoo/addons/product_manufacturer/i18n/ja.po
odoo/addons/product_manufacturer/i18n/lt.po
odoo/addons/product_manufacturer/i18n/lv.po
odoo/addons/product_manufacturer/i18n/mk.po
odoo/addons/product_manufacturer/i18n/mn.po
odoo/addons/product_manufacturer/i18n/nb.po
odoo/addons/product_manufacturer/i18n/nl.po
odoo/addons/product_manufacturer/i18n/nl_NL.po
odoo/addons/product_manufacturer/i18n/pl.po
odoo/addons/product_manufacturer/i18n/product_manufacturer.pot
odoo/addons/product_manufacturer/i18n/pt.po
odoo/addons/product_manufacturer/i18n/pt_BR.po
odoo/addons/product_manufacturer/i18n/ro.po
odoo/addons/product_manufacturer/i18n/ru.po
odoo/addons/product_manufacturer/i18n/sl.po
odoo/addons/product_manufacturer/i18n/sr.po
odoo/addons/product_manufacturer/i18n/sr@latin.po
odoo/addons/product_manufacturer/i18n/sv.po
odoo/addons/product_manufacturer/i18n/tr.po
odoo/addons/product_manufacturer/i18n/zh_CN.po
odoo13_addon_product_manufacturer-13.0.2.1.0.dist-info/METADATA
odoo13_addon_product_manufacturer-13.0.2.1.0.dist-info/WHEEL
odoo13_addon_product_manufacturer-13.0.2.1.0.dist-info/top_level.txt
odoo13_addon_product_manufacturer-13.0.2.1.0.dist-info/RECORD
